LICENSE
MANIFEST.in
README.md
pyproject.toml
basic_tutorial_files/basic_tutorial_22_1.png
basic_tutorial_files/basic_tutorial_24_1.png
src/lanfactory/__init__.py
src/lanfactory.egg-info/PKG-INFO
src/lanfactory.egg-info/SOURCES.txt
src/lanfactory.egg-info/dependency_links.txt
src/lanfactory.egg-info/entry_points.txt
src/lanfactory.egg-info/requires.txt
src/lanfactory.egg-info/top_level.txt
src/lanfactory/cli/config_network_training_lan.yaml
src/lanfactory/cli/jax_train.py
src/lanfactory/cli/torch_train.py
src/lanfactory/cli/utils.py
src/lanfactory/config/__init__.py
src/lanfactory/config/network_configs.py
src/lanfactory/onnx/__init__.py
src/lanfactory/onnx/transform_onnx.py
src/lanfactory/trainers/__init__.py
src/lanfactory/trainers/jax_mlp.py
src/lanfactory/trainers/torch_mlp.py
src/lanfactory/utils/__init__.py
src/lanfactory/utils/util_funs.py
tests/test_end_to_end_jax.py
tests/test_end_to_end_torch.py
tests/test_fixtures.py