Metadata-Version: 2.4
Name: lanfactory
Version: 0.6.0
Summary: Package with convenience functions to train LANs
Author-email: Alexander Fengler <alexander_fengler@brown.edu>, Carlos Paniagua <carlos_paniagua@brown.edu>
License: MIT License
Project-URL: Homepage, https://github.com/lnccbrown/LANFactory
Project-URL: Bug Tracker, https://github.com/lnccbrown/LANFactory/issues
Keywords: LANs,generative models,cognitive science,neuroscience,sbi
Classifier: Development Status :: 1 - Planning
Classifier: Environment :: Console
Classifier: License :: OSI Approved :: MIT License
Classifier: Programming Language :: Python
Classifier: Topic :: Scientific/Engineering
Requires-Python: <3.13,>3.10
License-File: LICENSE
Requires-Dist: ssm-simulators>=0.10.0
Requires-Dist: scipy>=1.15.2
Requires-Dist: pandas>=2.2.3
Requires-Dist: torch>=2.7.0
Requires-Dist: flax>=0.10.6
Requires-Dist: tqdm>=4.67.1
Requires-Dist: frozendict>=2.4.6
Requires-Dist: onnx>=1.17.0
Requires-Dist: matplotlib>=3.10.1
Provides-Extra: viz
Requires-Dist: wandb>=0.19.11; extra == "viz"
Dynamic: license-file
